manimalai/__init__.py
manimalai/__version__.py
manimalai/arena_config.py
manimalai/environment.py
manimalai/configurations/1-1-1.yml
manimalai/configurations/1-1-2.yml
manimalai/configurations/1-1-3.yml
manimalai/configurations/1-10-1.yml
manimalai/configurations/1-10-2.yml
manimalai/configurations/1-10-3.yml
manimalai/configurations/1-11-1.yml
manimalai/configurations/1-11-2.yml
manimalai/configurations/1-11-3.yml
manimalai/configurations/1-12-1.yml
manimalai/configurations/1-12-2.yml
manimalai/configurations/1-12-3.yml
manimalai/configurations/1-13-1.yml
manimalai/configurations/1-13-2.yml
manimalai/configurations/1-13-3.yml
manimalai/configurations/1-14-1.yml
manimalai/configurations/1-14-2.yml
manimalai/configurations/1-14-3.yml
manimalai/configurations/1-15-1.yml
manimalai/configurations/1-15-2.yml
manimalai/configurations/1-15-3.yml
manimalai/configurations/1-16-1.yml
manimalai/configurations/1-16-2.yml
manimalai/configurations/1-16-3.yml
manimalai/configurations/1-17-1.yml
manimalai/configurations/1-17-2.yml
manimalai/configurations/1-17-3.yml
manimalai/configurations/1-18-1.yml
manimalai/configurations/1-18-2.yml
manimalai/configurations/1-18-3.yml
manimalai/configurations/1-19-1.yml
manimalai/configurations/1-19-2.yml
manimalai/configurations/1-19-3.yml
manimalai/configurations/1-2-1.yml
manimalai/configurations/1-2-2.yml
manimalai/configurations/1-2-3.yml
manimalai/configurations/1-20-1.yml
manimalai/configurations/1-20-2.yml
manimalai/configurations/1-20-3.yml
manimalai/configurations/1-21-1.yml
manimalai/configurations/1-21-2.yml
manimalai/configurations/1-21-3.yml
manimalai/configurations/1-22-1.yml
manimalai/configurations/1-22-2.yml
manimalai/configurations/1-22-3.yml
manimalai/configurations/1-23-1.yml
manimalai/configurations/1-23-2.yml
manimalai/configurations/1-23-3.yml
manimalai/configurations/1-24-1.yml
manimalai/configurations/1-24-2.yml
manimalai/configurations/1-24-3.yml
manimalai/configurations/1-25-1.yml
manimalai/configurations/1-25-2.yml
manimalai-0.0.3.dist-info/LICENSE
manimalai-0.0.3.dist-info/METADATA
manimalai-0.0.3.dist-info/WHEEL
manimalai-0.0.3.dist-info/top_level.txt
manimalai-0.0.3.dist-info/RECORD
