Metadata-Version: 2.1
Name: manimalai
Version: 0.0.3
Summary: AnimalAI clone learning environment
Home-page: https://github.com/miyosuda/manimalai
Author: Kosuke Miyoshi
Author-email: miyosuda@gmail.com
License: Apache 2.0
Keywords: animalai,ai,deep learning,reinforcement learning,research
Platform: UNKNOWN
Classifier: Development Status :: 3 - Alpha
Classifier: Intended Audience :: Science/Research
Classifier: Topic :: Scientific/Engineering :: Artificial Intelligence
Classifier: License :: OSI Approved :: Apache Software License
Classifier: Programming Language :: Python :: 3
Classifier: Programming Language :: Python :: 3.5
Classifier: Programming Language :: Python :: 3.6
Classifier: Programming Language :: Python :: 3.7
Classifier: Programming Language :: Python :: 3.8
Requires-Dist: gym (>=0.18.0)
Requires-Dist: rodentia (>=0.0.8)
Requires-Dist: PyYAML (>=5.3)
